konthaina_khqr/__init__.py
konthaina_khqr/cli.py
konthaina_khqr/crc16.py
konthaina_khqr/decode.py
konthaina_khqr/enums.py
konthaina_khqr/exceptions.py
konthaina_khqr/generator.py
konthaina_khqr/py.typed
konthaina_khqr/tlv.py
konthaina_khqr/verify.py
konthaina_khqr-0.1.7.dist-info/licenses/LICENSE
konthaina_khqr-0.1.7.dist-info/METADATA
konthaina_khqr-0.1.7.dist-info/WHEEL
konthaina_khqr-0.1.7.dist-info/entry_points.txt
konthaina_khqr-0.1.7.dist-info/top_level.txt
konthaina_khqr-0.1.7.dist-info/RECORD
