Metadata-Version: 2.4
Name: konthaina-khqr
Version: 0.1.7
Summary: KHQR / EMVCo merchant-presented QR payload generator for Bakong (Cambodia), with CRC16 verification.
Author-email: Konthaina <konthaina87@gmail.com>
License: MIT License
Project-URL: Homepage, https://github.com/Konthaina/khqr-python
Project-URL: Repository, https://github.com/Konthaina/khqr-python
Project-URL: Issues, https://github.com/Konthaina/khqr-python/issues
Keywords: khqr,bakong,emvco,qr,cambodia
Classifier: Development Status :: 3 - Alpha
Classifier: License :: OSI Approved :: MIT License
Classifier: Programming Language :: Python :: 3
Classifier: Programming Language :: Python :: 3 :: Only
Classifier: Programming Language :: Python :: 3.9
Classifier: Programming Language :: Python :: 3.10
Classifier: Programming Language :: Python :: 3.11
Classifier: Programming Language :: Python :: 3.12
Classifier: Programming Language :: Python :: 3.13
Classifier: Typing :: Typed
Requires-Python: >=3.9
License-File: LICENSE
Provides-Extra: qrcode
Requires-Dist: qrcode[pil]>=7.0; extra == "qrcode"
Provides-Extra: dev
Requires-Dist: pytest>=8; extra == "dev"
Requires-Dist: ruff>=0.6; extra == "dev"
Requires-Dist: mypy>=1.11; extra == "dev"
Requires-Dist: build>=1.2; extra == "dev"
Requires-Dist: twine>=5.1; extra == "dev"
Dynamic: license-file
